{"propertiesBar":{"properties":[{"name":"Layout","expanded":true,"children":[{"name":"Size","expanded":true,"children":[]}]},{"name":"Effects","expanded":true,"children":[]},{"name":"Editor","expanded":true,"children":[{"name":"Margins","expanded":false,"children":[]},{"name":"Grid size","expanded":false,"children":[]},{"name":"Grid offset","expanded":false,"children":[]}]}],"scrollPosition":0},"grid":{"show":true,"snap":false,"width":320,"height":240,"offsetX":0,"offsetY":0},"marginWidth":1000,"marginHeight":1000,"showCollisionPolygons":false,"showMeshes":false,"showTranslucentInactiveLayers":false,"showSceneGraphConnections":true,"tabColor":[0.9999999999999999,0.95,0.8000000000000002,1],"tabTextColor":null,"layers":[{"name":"Background","propertiesBar":{"properties":[{"name":"Layer properties","expanded":true,"children":[]},{"name":"Scroll & zoom","expanded":true,"children":[{"name":"Parallax","expanded":false,"children":[]}]},{"name":"Appearance","expanded":true,"children":[]},{"name":"Effects","expanded":true,"children":[]},{"name":"Editor","expanded":true,"children":[]}],"scrollPosition":0},"visibleInEditor":true,"locked":false,"parallaxInEditor":false,"opacity":1,"translucent":false},{"name":"Gizmos","propertiesBar":{"properties":[{"name":"Layer properties","expanded":true,"children":[]},{"name":"Scroll & zoom","expanded":true,"children":[{"name":"Parallax","expanded":false,"children":[]}]},{"name":"Appearance","expanded":true,"children":[]},{"name":"Effects","expanded":true,"children":[]},{"name":"Editor","expanded":true,"children":[]}],"scrollPosition":0},"visibleInEditor":true,"locked":false,"parallaxInEditor":false,"opacity":1,"translucent":false},{"name":"Effects","propertiesBar":{"properties":[{"name":"Layer properties","expanded":true,"children":[]},{"name":"Scroll & zoom","expanded":true,"children":[{"name":"Parallax","expanded":false,"children":[]}]},{"name":"Appearance","expanded":true,"children":[]},{"name":"Effects","expanded":true,"children":[{"name":"ScanLines","expanded":true,"children":[]}]},{"name":"Editor","expanded":true,"children":[]}],"scrollPosition":0},"visibleInEditor":true,"locked":false,"parallaxInEditor":false,"opacity":1,"translucent":false},{"name":"Whiteblock","propertiesBar":{"properties":[{"name":"Layer properties","expanded":true,"children":[]},{"name":"Scroll & zoom","expanded":true,"children":[{"name":"Parallax","expanded":false,"children":[]}]},{"name":"Appearance","expanded":true,"children":[]},{"name":"Effects","expanded":true,"children":[{"name":"Outline","expanded":true,"children":[]},{"name":"Outline2","expanded":true,"children":[]}]},{"name":"Editor","expanded":true,"children":[]}],"scrollPosition":0},"visibleInEditor":true,"locked":false,"parallaxInEditor":false,"opacity":1,"translucent":false},{"name":"3D","propertiesBar":{"properties":[{"name":"Layer properties","expanded":true,"children":[]},{"name":"Scroll & zoom","expanded":true,"children":[{"name":"Parallax","expanded":false,"children":[]}]},{"name":"Appearance","expanded":true,"children":[]},{"name":"Effects","expanded":true,"children":[]},{"name":"Editor","expanded":true,"children":[]}],"scrollPosition":0},"visibleInEditor":true,"locked":false,"parallaxInEditor":false,"opacity":1,"translucent":false},{"name":"Controllers","propertiesBar":{"properties":[{"name":"Layer properties","expanded":true,"children":[]},{"name":"Scroll & zoom","expanded":true,"children":[{"name":"Parallax","expanded":false,"children":[]}]},{"name":"Appearance","expanded":true,"children":[]},{"name":"Effects","expanded":true,"children":[]},{"name":"Editor","expanded":true,"children":[]}],"scrollPosition":0},"visibleInEditor":true,"locked":false,"parallaxInEditor":false,"opacity":1,"translucent":false},{"name":"UI_World","propertiesBar":{"properties":[{"name":"Layer properties","expanded":true,"children":[]},{"name":"Scroll & zoom","expanded":true,"children":[{"name":"Parallax","expanded":false,"children":[]}]},{"name":"Appearance","expanded":true,"children":[]},{"name":"Effects","expanded":true,"children":[]},{"name":"Editor","expanded":true,"children":[]}],"scrollPosition":0},"visibleInEditor":true,"locked":false,"parallaxInEditor":false,"opacity":1,"translucent":false},{"name":"UI","propertiesBar":{"properties":[{"name":"Layer properties","expanded":true,"children":[]},{"name":"Scroll & zoom","expanded":true,"children":[{"name":"Parallax","expanded":false,"children":[]}]},{"name":"Appearance","expanded":true,"children":[]},{"name":"Effects","expanded":true,"children":[{"name":"Outline","expanded":true,"children":[]}]},{"name":"Editor","expanded":true,"children":[]}],"scrollPosition":0},"visibleInEditor":true,"locked":false,"parallaxInEditor":false,"opacity":1,"translucent":false},{"name":"DebugInfo","propertiesBar":{"properties":[{"name":"Layer properties","expanded":true,"children":[]},{"name":"Scroll & zoom","expanded":true,"children":[{"name":"Parallax","expanded":false,"children":[]}]},{"name":"Appearance","expanded":true,"children":[]},{"name":"Effects","expanded":true,"children":[{"name":"Outline","expanded":true,"children":[]}]},{"name":"Editor","expanded":true,"children":[]}],"scrollPosition":0},"visibleInEditor":false,"locked":false,"parallaxInEditor":false,"opacity":1,"translucent":false}],"instanceCollections":[{"uids":[254,255,256,262],"properties":{"properties":[{"name":"Object type properties","expanded":true,"children":[]},{"name":"Common","expanded":true,"children":[{"name":"Position","expanded":false,"children":[]},{"name":"Size","expanded":false,"children":[]}]},{"name":"Instance variables","expanded":true,"children":[{"name":"Inherited from 'fEnemies'","expanded":true,"children":[]}]},{"name":"Behaviors","expanded":true,"children":[{"name":"Tween [fEnemies]","expanded":true,"children":[]}]},{"name":"Effects","expanded":true,"children":[]},{"name":"Container","expanded":true,"children":[]},{"name":"Hierarchy","expanded":true,"children":[]},{"name":"Properties","expanded":true,"children":[]}],"scrollPosition":0}},{"uids":[263,264,265,324],"properties":{"properties":[{"name":"Object type properties","expanded":true,"children":[]},{"name":"Common","expanded":true,"children":[{"name":"Position","expanded":false,"children":[]},{"name":"Size","expanded":false,"children":[]}]},{"name":"Effects","expanded":true,"children":[]},{"name":"Hierarchy","expanded":true,"children":[]},{"name":"Properties","expanded":true,"children":[]}],"scrollPosition":0}},{"uids":[254,255,310,311],"properties":{"properties":[{"name":"Object type properties","expanded":true,"children":[]},{"name":"Common","expanded":true,"children":[{"name":"Position","expanded":false,"children":[]},{"name":"Size","expanded":false,"children":[]}]},{"name":"Instance variables","expanded":true,"children":[]},{"name":"Behaviors","expanded":true,"children":[{"name":"Solid","expanded":true,"children":[]}]},{"name":"Effects","expanded":true,"children":[]},{"name":"Container","expanded":true,"children":[]},{"name":"Properties","expanded":true,"children":[]}],"scrollPosition":0}},{"uids":[256,257,258,259],"properties":{"properties":[{"name":"Object type properties","expanded":true,"children":[]},{"name":"Common","expanded":true,"children":[{"name":"Position","expanded":false,"children":[]},{"name":"Size","expanded":false,"children":[]}]},{"name":"Instance variables","expanded":true,"children":[]},{"name":"Behaviors","expanded":true,"children":[{"name":"Solid","expanded":true,"children":[]}]},{"name":"Effects","expanded":true,"children":[]},{"name":"Container","expanded":true,"children":[]},{"name":"Properties","expanded":true,"children":[]}],"scrollPosition":0}},{"uids":[266,268,272,274],"properties":{"properties":[{"name":"Common","expanded":true,"children":[{"name":"Position","expanded":false,"children":[]},{"name":"Size","expanded":false,"children":[]}]},{"name":"Effects","expanded":true,"children":[]}],"scrollPosition":0}},{"uids":[260,275,314,325,326,327,328],"properties":{"properties":[{"name":"Object type properties","expanded":true,"children":[]},{"name":"Common","expanded":true,"children":[{"name":"Position","expanded":false,"children":[]},{"name":"Size","expanded":false,"children":[]}]},{"name":"Instance variables","expanded":true,"children":[]},{"name":"Behaviors","expanded":true,"children":[{"name":"Solid","expanded":true,"children":[]}]},{"name":"Effects","expanded":true,"children":[]},{"name":"Container","expanded":true,"children":[]},{"name":"Properties","expanded":true,"children":[]}],"scrollPosition":0}},{"uids":[270,309,312,313,314,315,325],"properties":{"properties":[{"name":"Object type properties","expanded":true,"children":[]},{"name":"Common","expanded":true,"children":[{"name":"Position","expanded":false,"children":[]},{"name":"Size","expanded":false,"children":[]}]},{"name":"Effects","expanded":true,"children":[]},{"name":"Properties","expanded":true,"children":[]}],"scrollPosition":0}},{"uids":[260,270,309,312,313,315,325],"properties":{"properties":[{"name":"Object type properties","expanded":true,"children":[]},{"name":"Common","expanded":true,"children":[{"name":"Position","expanded":false,"children":[]},{"name":"Size","expanded":false,"children":[]}]},{"name":"Effects","expanded":true,"children":[]},{"name":"Properties","expanded":true,"children":[]}],"scrollPosition":0}},{"uids":[260,314,325,326,327,328],"properties":{"properties":[{"name":"Object type properties","expanded":true,"children":[]},{"name":"Common","expanded":true,"children":[{"name":"Position","expanded":false,"children":[]},{"name":"Size","expanded":false,"children":[]}]},{"name":"Instance variables","expanded":true,"children":[]},{"name":"Behaviors","expanded":true,"children":[{"name":"Solid","expanded":true,"children":[]}]},{"name":"Effects","expanded":true,"children":[]},{"name":"Container","expanded":true,"children":[]},{"name":"Properties","expanded":true,"children":[]}],"scrollPosition":0}},{"uids":[270,309,312,313,314,315],"properties":{"properties":[{"name":"Object type properties","expanded":true,"children":[]},{"name":"Common","expanded":true,"children":[{"name":"Position","expanded":false,"children":[]},{"name":"Size","expanded":false,"children":[]}]},{"name":"Effects","expanded":true,"children":[]},{"name":"Properties","expanded":true,"children":[]}],"scrollPosition":0}},{"uids":[270,309,312,313,315,325],"properties":{"properties":[{"name":"Object type properties","expanded":true,"children":[]},{"name":"Common","expanded":true,"children":[{"name":"Position","expanded":false,"children":[]},{"name":"Size","expanded":false,"children":[]}]},{"name":"Effects","expanded":true,"children":[]},{"name":"Properties","expanded":true,"children":[]}],"scrollPosition":0}},{"uids":[316,317,318,319,320],"properties":{"properties":[{"name":"Object type properties","expanded":true,"children":[]},{"name":"Common","expanded":true,"children":[{"name":"Position","expanded":false,"children":[]},{"name":"Size","expanded":false,"children":[]}]},{"name":"Instance variables","expanded":true,"children":[{"name":"Inherited from 'fEnemies'","expanded":true,"children":[]}]},{"name":"Behaviors","expanded":true,"children":[{"name":"Tween [fEnemies]","expanded":true,"children":[]}]},{"name":"Effects","expanded":true,"children":[]},{"name":"Container","expanded":true,"children":[]},{"name":"Hierarchy","expanded":true,"children":[]},{"name":"Properties","expanded":true,"children":[]}],"scrollPosition":0}},{"uids":[262,263,266,268,274],"properties":{"properties":[{"name":"Common","expanded":true,"children":[{"name":"Position","expanded":false,"children":[]},{"name":"Size","expanded":false,"children":[]}]},{"name":"Effects","expanded":true,"children":[]}],"scrollPosition":0}},{"uids":[262,263,266,268,272,274],"properties":{"properties":[{"name":"Common","expanded":true,"children":[{"name":"Position","expanded":false,"children":[]},{"name":"Size","expanded":false,"children":[]}]},{"name":"Effects","expanded":true,"children":[]}],"scrollPosition":0}},{"uids":[314,325],"properties":{"properties":[{"name":"Object type properties","expanded":true,"children":[]},{"name":"Common","expanded":true,"children":[{"name":"Position","expanded":false,"children":[]},{"name":"Size","expanded":false,"children":[]}]},{"name":"Instance variables","expanded":true,"children":[]},{"name":"Behaviors","expanded":true,"children":[{"name":"Solid","expanded":true,"children":[]}]},{"name":"Effects","expanded":true,"children":[]},{"name":"Container","expanded":true,"children":[]},{"name":"Properties","expanded":true,"children":[]}],"scrollPosition":0}},{"uids":[326,327],"properties":{"properties":[{"name":"Object type properties","expanded":true,"children":[]},{"name":"Common","expanded":true,"children":[{"name":"Position","expanded":false,"children":[]},{"name":"Size","expanded":false,"children":[]}]},{"name":"Instance variables","expanded":true,"children":[]},{"name":"Behaviors","expanded":true,"children":[{"name":"Solid","expanded":true,"children":[]}]},{"name":"Effects","expanded":true,"children":[]},{"name":"Container","expanded":true,"children":[]},{"name":"Properties","expanded":true,"children":[]}],"scrollPosition":0}},{"uids":[254,255],"properties":{"properties":[{"name":"Object type properties","expanded":true,"children":[]},{"name":"Common","expanded":true,"children":[{"name":"Position","expanded":false,"children":[]},{"name":"Size","expanded":false,"children":[]}]},{"name":"Instance variables","expanded":true,"children":[]},{"name":"Behaviors","expanded":true,"children":[{"name":"Solid","expanded":true,"children":[]}]},{"name":"Effects","expanded":true,"children":[]},{"name":"Container","expanded":true,"children":[]},{"name":"Properties","expanded":true,"children":[]}],"scrollPosition":0}},{"uids":[310,311],"properties":{"properties":[{"name":"Object type properties","expanded":true,"children":[]},{"name":"Common","expanded":true,"children":[{"name":"Position","expanded":false,"children":[]},{"name":"Size","expanded":false,"children":[]}]},{"name":"Instance variables","expanded":true,"children":[]},{"name":"Behaviors","expanded":true,"children":[{"name":"Solid","expanded":true,"children":[]}]},{"name":"Effects","expanded":true,"children":[]},{"name":"Container","expanded":true,"children":[]},{"name":"Properties","expanded":true,"children":[]}],"scrollPosition":0}},{"uids":[241,264],"properties":{"properties":[{"name":"Object type properties","expanded":true,"children":[]},{"name":"Common","expanded":true,"children":[{"name":"Position","expanded":false,"children":[]},{"name":"Size","expanded":false,"children":[]}]},{"name":"Effects","expanded":true,"children":[]},{"name":"Properties","expanded":true,"children":[]}],"scrollPosition":0}},{"uids":[264,265],"properties":{"properties":[{"name":"Object type properties","expanded":true,"children":[]},{"name":"Common","expanded":true,"children":[{"name":"Position","expanded":false,"children":[]},{"name":"Size","expanded":false,"children":[]}]},{"name":"Effects","expanded":true,"children":[]},{"name":"Properties","expanded":true,"children":[]}],"scrollPosition":0}},{"uids":[312,313],"properties":{"properties":[{"name":"Object type properties","expanded":true,"children":[]},{"name":"Common","expanded":true,"children":[{"name":"Position","expanded":false,"children":[]},{"name":"Size","expanded":false,"children":[]}]},{"name":"Instance variables","expanded":true,"children":[{"name":"Inherited from 'fEnemies'","expanded":true,"children":[]}]},{"name":"Behaviors","expanded":true,"children":[{"name":"Tween [fEnemies]","expanded":true,"children":[]}]},{"name":"Effects","expanded":true,"children":[]},{"name":"Container","expanded":true,"children":[]},{"name":"Hierarchy","expanded":true,"children":[]},{"name":"Properties","expanded":true,"children":[]}],"scrollPosition":0}},{"uids":[270,309],"properties":{"properties":[{"name":"Object type properties","expanded":true,"children":[]},{"name":"Common","expanded":true,"children":[{"name":"Position","expanded":false,"children":[]},{"name":"Size","expanded":false,"children":[]}]},{"name":"Instance variables","expanded":true,"children":[{"name":"Inherited from 'fEnemies'","expanded":true,"children":[]}]},{"name":"Behaviors","expanded":true,"children":[{"name":"Tween [fEnemies]","expanded":true,"children":[]}]},{"name":"Effects","expanded":true,"children":[]},{"name":"Container","expanded":true,"children":[]},{"name":"Hierarchy","expanded":true,"children":[]},{"name":"Properties","expanded":true,"children":[]}],"scrollPosition":0}},{"uids":[260,261],"properties":{"properties":[{"name":"Object type properties","expanded":true,"children":[]},{"name":"Common","expanded":true,"children":[{"name":"Position","expanded":false,"children":[]},{"name":"Size","expanded":false,"children":[]}]},{"name":"Instance variables","expanded":true,"children":[]},{"name":"Behaviors","expanded":true,"children":[{"name":"Solid","expanded":true,"children":[]}]},{"name":"Effects","expanded":true,"children":[]},{"name":"Container","expanded":true,"children":[]},{"name":"Hierarchy","expanded":true,"children":[]},{"name":"Properties","expanded":true,"children":[]}],"scrollPosition":0}},{"uids":[260,261],"properties":{"properties":[{"name":"Object type properties","expanded":true,"children":[]},{"name":"Common","expanded":true,"children":[{"name":"Position","expanded":false,"children":[]},{"name":"Size","expanded":false,"children":[]}]},{"name":"Effects","expanded":true,"children":[]},{"name":"Properties","expanded":true,"children":[]}],"scrollPosition":0}},{"uids":[327,328],"properties":{"properties":[{"name":"Object type properties","expanded":true,"children":[]},{"name":"Common","expanded":true,"children":[{"name":"Position","expanded":false,"children":[]},{"name":"Size","expanded":false,"children":[]}]},{"name":"Instance variables","expanded":true,"children":[]},{"name":"Behaviors","expanded":true,"children":[{"name":"Solid","expanded":true,"children":[]}]},{"name":"Effects","expanded":true,"children":[]},{"name":"Container","expanded":true,"children":[]},{"name":"Hierarchy","expanded":true,"children":[]},{"name":"Properties","expanded":true,"children":[]}],"scrollPosition":0}},{"uids":[313,315],"properties":{"properties":[{"name":"Object type properties","expanded":true,"children":[]},{"name":"Common","expanded":true,"children":[{"name":"Position","expanded":false,"children":[]},{"name":"Size","expanded":false,"children":[]}]},{"name":"Instance variables","expanded":true,"children":[{"name":"Inherited from 'fEnemies'","expanded":true,"children":[]}]},{"name":"Behaviors","expanded":true,"children":[{"name":"Tween [fEnemies]","expanded":true,"children":[]}]},{"name":"Effects","expanded":true,"children":[]},{"name":"Container","expanded":true,"children":[]},{"name":"Hierarchy","expanded":true,"children":[]},{"name":"Properties","expanded":true,"children":[]}],"scrollPosition":0}},{"uids":[415,416],"properties":{"properties":[{"name":"Object type properties","expanded":true,"children":[]},{"name":"Common","expanded":true,"children":[{"name":"Position","expanded":false,"children":[]},{"name":"Size","expanded":false,"children":[]}]},{"name":"Instance variables","expanded":true,"children":[]},{"name":"Behaviors","expanded":true,"children":[]},{"name":"Effects","expanded":true,"children":[]},{"name":"Container","expanded":true,"children":[]},{"name":"Properties","expanded":true,"children":[]}],"scrollPosition":0}},{"uids":[15,77,254,257,259,262,263,266,268,270,272,274,275,309,310,312,313,314,315,316,317,318,320,323,325,326,327,412,413,414,415,416,417,418,419,420,421,422,423,424,425,426,427,428,430,431],"properties":{"properties":[{"name":"Common","expanded":true,"children":[{"name":"Position","expanded":false,"children":[]},{"name":"Size","expanded":false,"children":[]}]},{"name":"Effects","expanded":true,"children":[]}],"scrollPosition":0}},{"uids":[77,254,259,260,261,262,263,265,266,268,270,272,274,275,309,310,311,312,313,314,315,318,320,323,325,326,327,328,411,412,413,414,415,416,417,418,419,420,421,422,423,424,425],"properties":{"properties":[{"name":"Common","expanded":true,"children":[{"name":"Position","expanded":false,"children":[]},{"name":"Size","expanded":false,"children":[]}]},{"name":"Effects","expanded":true,"children":[]}],"scrollPosition":0}},{"uids":[260],"properties":{"properties":[{"name":"Object type properties","expanded":true,"children":[]},{"name":"Common","expanded":true,"children":[{"name":"Position","expanded":false,"children":[]},{"name":"Size","expanded":false,"children":[]}]},{"name":"Instance variables","expanded":true,"children":[]},{"name":"Behaviors","expanded":true,"children":[{"name":"Solid","expanded":true,"children":[]}]},{"name":"Effects","expanded":true,"children":[]},{"name":"Container","expanded":true,"children":[]},{"name":"Properties","expanded":true,"children":[]}],"scrollPosition":0}},{"uids":[265],"properties":{"properties":[{"name":"Object type properties","expanded":true,"children":[]},{"name":"Common","expanded":true,"children":[{"name":"Position","expanded":false,"children":[]},{"name":"Size","expanded":false,"children":[]}]},{"name":"Instance variables","expanded":true,"children":[]},{"name":"Behaviors","expanded":true,"children":[]},{"name":"Effects","expanded":true,"children":[]},{"name":"Container","expanded":true,"children":[]},{"name":"Properties","expanded":true,"children":[]}],"scrollPosition":0}},{"uids":[244],"properties":{"properties":[{"name":"Object type properties","expanded":true,"children":[]},{"name":"Common","expanded":true,"children":[{"name":"Position","expanded":false,"children":[]},{"name":"Size","expanded":false,"children":[]}]},{"name":"Instance variables","expanded":true,"children":[{"name":"Inherited from 'oSlices'","expanded":true,"children":[]}]},{"name":"Behaviors","expanded":true,"children":[{"name":"Pin [oSlices]","expanded":true,"children":[]}]},{"name":"Effects","expanded":true,"children":[]},{"name":"Container","expanded":true,"children":[]},{"name":"Properties","expanded":true,"children":[]}],"scrollPosition":0}},{"uids":[309],"properties":{"properties":[{"name":"Object type properties","expanded":true,"children":[]},{"name":"Common","expanded":true,"children":[{"name":"Position","expanded":false,"children":[]},{"name":"Size","expanded":false,"children":[]}]},{"name":"Instance variables","expanded":true,"children":[{"name":"Inherited from 'fEnemies'","expanded":true,"children":[]}]},{"name":"Behaviors","expanded":true,"children":[{"name":"Tween [fEnemies]","expanded":true,"children":[]}]},{"name":"Effects","expanded":true,"children":[]},{"name":"Container","expanded":true,"children":[]},{"name":"Hierarchy","expanded":true,"children":[]},{"name":"Properties","expanded":true,"children":[]}],"scrollPosition":0}},{"uids":[313],"properties":{"properties":[{"name":"Object type properties","expanded":true,"children":[]},{"name":"Common","expanded":true,"children":[{"name":"Position","expanded":false,"children":[]},{"name":"Size","expanded":false,"children":[]}]},{"name":"Instance variables","expanded":true,"children":[{"name":"Inherited from 'fEnemies'","expanded":true,"children":[]}]},{"name":"Behaviors","expanded":true,"children":[{"name":"Tween [fEnemies]","expanded":true,"children":[]}]},{"name":"Effects","expanded":true,"children":[]},{"name":"Container","expanded":true,"children":[]},{"name":"Hierarchy","expanded":true,"children":[]},{"name":"Properties","expanded":true,"children":[]}],"scrollPosition":0}},{"uids":[315],"properties":{"properties":[{"name":"Object type properties","expanded":true,"children":[]},{"name":"Common","expanded":true,"children":[{"name":"Position","expanded":false,"children":[]},{"name":"Size","expanded":false,"children":[]}]},{"name":"Instance variables","expanded":true,"children":[{"name":"Inherited from 'fEnemies'","expanded":true,"children":[]}]},{"name":"Behaviors","expanded":true,"children":[{"name":"Tween [fEnemies]","expanded":true,"children":[]}]},{"name":"Effects","expanded":true,"children":[]},{"name":"Container","expanded":true,"children":[]},{"name":"Hierarchy","expanded":true,"children":[]},{"name":"Properties","expanded":true,"children":[]}],"scrollPosition":0}},{"uids":[312],"properties":{"properties":[{"name":"Object type properties","expanded":true,"children":[]},{"name":"Common","expanded":true,"children":[{"name":"Position","expanded":false,"children":[]},{"name":"Size","expanded":false,"children":[]}]},{"name":"Instance variables","expanded":true,"children":[{"name":"Inherited from 'fEnemies'","expanded":true,"children":[]}]},{"name":"Behaviors","expanded":true,"children":[{"name":"Tween [fEnemies]","expanded":true,"children":[]}]},{"name":"Effects","expanded":true,"children":[]},{"name":"Container","expanded":true,"children":[]},{"name":"Hierarchy","expanded":true,"children":[]},{"name":"Properties","expanded":true,"children":[]}],"scrollPosition":0}},{"uids":[325],"properties":{"properties":[{"name":"Object type properties","expanded":true,"children":[]},{"name":"Common","expanded":true,"children":[{"name":"Position","expanded":false,"children":[]},{"name":"Size","expanded":false,"children":[]}]},{"name":"Instance variables","expanded":true,"children":[]},{"name":"Behaviors","expanded":true,"children":[{"name":"Solid","expanded":true,"children":[]}]},{"name":"Effects","expanded":true,"children":[]},{"name":"Container","expanded":true,"children":[]},{"name":"Properties","expanded":true,"children":[]}],"scrollPosition":0}},{"uids":[260],"properties":{"properties":[{"name":"Object type properties","expanded":true,"children":[]},{"name":"Common","expanded":true,"children":[{"name":"Position","expanded":false,"children":[]},{"name":"Size","expanded":false,"children":[]}]},{"name":"Instance variables","expanded":true,"children":[]},{"name":"Behaviors","expanded":true,"children":[{"name":"Solid","expanded":true,"children":[]}]},{"name":"Effects","expanded":true,"children":[]},{"name":"Container","expanded":true,"children":[]},{"name":"Properties","expanded":true,"children":[]}],"scrollPosition":0}},{"uids":[328],"properties":{"properties":[{"name":"Object type properties","expanded":true,"children":[]},{"name":"Common","expanded":true,"children":[{"name":"Position","expanded":false,"children":[]},{"name":"Size","expanded":false,"children":[]}]},{"name":"Instance variables","expanded":true,"children":[]},{"name":"Behaviors","expanded":true,"children":[{"name":"Solid","expanded":true,"children":[]}]},{"name":"Effects","expanded":true,"children":[]},{"name":"Container","expanded":true,"children":[]},{"name":"Properties","expanded":true,"children":[]}],"scrollPosition":0}},{"uids":[327],"properties":{"properties":[{"name":"Object type properties","expanded":true,"children":[]},{"name":"Common","expanded":true,"children":[{"name":"Position","expanded":false,"children":[]},{"name":"Size","expanded":false,"children":[]}]},{"name":"Instance variables","expanded":true,"children":[]},{"name":"Behaviors","expanded":true,"children":[{"name":"Solid","expanded":true,"children":[]}]},{"name":"Effects","expanded":true,"children":[]},{"name":"Container","expanded":true,"children":[]},{"name":"Properties","expanded":true,"children":[]}],"scrollPosition":0}},{"uids":[310],"properties":{"properties":[{"name":"Object type properties","expanded":true,"children":[]},{"name":"Common","expanded":true,"children":[{"name":"Position","expanded":false,"children":[]},{"name":"Size","expanded":false,"children":[]}]},{"name":"Instance variables","expanded":true,"children":[]},{"name":"Behaviors","expanded":true,"children":[{"name":"Solid","expanded":true,"children":[]}]},{"name":"Effects","expanded":true,"children":[]},{"name":"Container","expanded":true,"children":[]},{"name":"Properties","expanded":true,"children":[]}],"scrollPosition":0}},{"uids":[261],"properties":{"properties":[{"name":"Object type properties","expanded":true,"children":[]},{"name":"Common","expanded":true,"children":[{"name":"Position","expanded":false,"children":[]},{"name":"Size","expanded":false,"children":[]}]},{"name":"Instance variables","expanded":true,"children":[]},{"name":"Behaviors","expanded":true,"children":[{"name":"Solid","expanded":true,"children":[]}]},{"name":"Effects","expanded":true,"children":[]},{"name":"Container","expanded":true,"children":[]},{"name":"Hierarchy","expanded":true,"children":[]},{"name":"Properties","expanded":true,"children":[]}],"scrollPosition":0}},{"uids":[261],"properties":{"properties":[{"name":"Object type properties","expanded":true,"children":[]},{"name":"Common","expanded":true,"children":[{"name":"Position","expanded":false,"children":[]},{"name":"Size","expanded":false,"children":[]}]},{"name":"Instance variables","expanded":true,"children":[]},{"name":"Behaviors","expanded":true,"children":[{"name":"Solid","expanded":true,"children":[]}]},{"name":"Effects","expanded":true,"children":[]},{"name":"Container","expanded":true,"children":[]},{"name":"Hierarchy","expanded":true,"children":[]},{"name":"Properties","expanded":true,"children":[]}],"scrollPosition":0}},{"uids":[260],"properties":{"properties":[{"name":"Object type properties","expanded":true,"children":[]},{"name":"Common","expanded":true,"children":[{"name":"Position","expanded":false,"children":[]},{"name":"Size","expanded":false,"children":[]}]},{"name":"Instance variables","expanded":true,"children":[]},{"name":"Behaviors","expanded":true,"children":[{"name":"Solid","expanded":true,"children":[]}]},{"name":"Effects","expanded":true,"children":[]},{"name":"Container","expanded":true,"children":[]},{"name":"Hierarchy","expanded":true,"children":[]},{"name":"Properties","expanded":true,"children":[]}],"scrollPosition":0}},{"uids":[325],"properties":{"properties":[{"name":"Object type properties","expanded":true,"children":[]},{"name":"Common","expanded":true,"children":[{"name":"Position","expanded":false,"children":[]},{"name":"Size","expanded":false,"children":[]}]},{"name":"Instance variables","expanded":true,"children":[]},{"name":"Behaviors","expanded":true,"children":[{"name":"Solid","expanded":true,"children":[]}]},{"name":"Effects","expanded":true,"children":[]},{"name":"Container","expanded":true,"children":[]},{"name":"Hierarchy","expanded":true,"children":[]},{"name":"Properties","expanded":true,"children":[]}],"scrollPosition":0}},{"uids":[266],"properties":{"properties":[{"name":"Object type properties","expanded":true,"children":[]},{"name":"Common","expanded":true,"children":[{"name":"Position","expanded":false,"children":[]},{"name":"Size","expanded":false,"children":[]}]},{"name":"Instance variables","expanded":true,"children":[]},{"name":"Behaviors","expanded":true,"children":[{"name":"ScrollTo","expanded":true,"children":[]},{"name":"8Direction","expanded":true,"children":[]},{"name":"Tween","expanded":true,"children":[]}]},{"name":"Effects","expanded":true,"children":[]},{"name":"Container","expanded":true,"children":[]},{"name":"Properties","expanded":true,"children":[]}],"scrollPosition":0}},{"uids":[311],"properties":{"properties":[{"name":"Object type properties","expanded":true,"children":[]},{"name":"Common","expanded":true,"children":[{"name":"Position","expanded":false,"children":[]},{"name":"Size","expanded":false,"children":[]}]},{"name":"Instance variables","expanded":true,"children":[]},{"name":"Behaviors","expanded":true,"children":[{"name":"Solid","expanded":true,"children":[]}]},{"name":"Effects","expanded":true,"children":[]},{"name":"Container","expanded":true,"children":[]},{"name":"Properties","expanded":true,"children":[]}],"scrollPosition":0}},{"uids":[327],"properties":{"properties":[{"name":"Object type properties","expanded":true,"children":[]},{"name":"Common","expanded":true,"children":[{"name":"Position","expanded":false,"children":[]},{"name":"Size","expanded":false,"children":[]}]},{"name":"Instance variables","expanded":true,"children":[]},{"name":"Behaviors","expanded":true,"children":[{"name":"Solid","expanded":true,"children":[]}]},{"name":"Effects","expanded":true,"children":[]},{"name":"Container","expanded":true,"children":[]},{"name":"Hierarchy","expanded":true,"children":[]},{"name":"Properties","expanded":true,"children":[]}],"scrollPosition":0}},{"uids":[328],"properties":{"properties":[{"name":"Object type properties","expanded":true,"children":[]},{"name":"Common","expanded":true,"children":[{"name":"Position","expanded":false,"children":[]},{"name":"Size","expanded":false,"children":[]}]},{"name":"Instance variables","expanded":true,"children":[]},{"name":"Behaviors","expanded":true,"children":[{"name":"Solid","expanded":true,"children":[]}]},{"name":"Effects","expanded":true,"children":[]},{"name":"Container","expanded":true,"children":[]},{"name":"Hierarchy","expanded":true,"children":[]},{"name":"Properties","expanded":true,"children":[]}],"scrollPosition":0}},{"uids":[412],"properties":{"properties":[{"name":"Object type properties","expanded":true,"children":[]},{"name":"Common","expanded":true,"children":[{"name":"Position","expanded":false,"children":[]},{"name":"Size","expanded":false,"children":[]}]},{"name":"Instance variables","expanded":true,"children":[]},{"name":"Behaviors","expanded":true,"children":[{"name":"Solid","expanded":true,"children":[]}]},{"name":"Effects","expanded":true,"children":[]},{"name":"Container","expanded":true,"children":[]},{"name":"Hierarchy","expanded":true,"children":[]},{"name":"Properties","expanded":true,"children":[]}],"scrollPosition":0}},{"uids":[309],"properties":{"properties":[{"name":"Object type properties","expanded":true,"children":[]},{"name":"Common","expanded":true,"children":[{"name":"Position","expanded":false,"children":[]},{"name":"Size","expanded":false,"children":[]}]},{"name":"Instance variables","expanded":true,"children":[]},{"name":"Behaviors","expanded":true,"children":[{"name":"Solid","expanded":true,"children":[]}]},{"name":"Effects","expanded":true,"children":[]},{"name":"Container","expanded":true,"children":[]},{"name":"Hierarchy","expanded":true,"children":[]},{"name":"Properties","expanded":true,"children":[]}],"scrollPosition":0}},{"uids":[310],"properties":{"properties":[{"name":"Object type properties","expanded":true,"children":[]},{"name":"Common","expanded":true,"children":[{"name":"Position","expanded":false,"children":[]},{"name":"Size","expanded":false,"children":[]}]},{"name":"Instance variables","expanded":true,"children":[]},{"name":"Behaviors","expanded":true,"children":[{"name":"Solid","expanded":true,"children":[]}]},{"name":"Effects","expanded":true,"children":[]},{"name":"Container","expanded":true,"children":[]},{"name":"Hierarchy","expanded":true,"children":[]},{"name":"Properties","expanded":true,"children":[]}],"scrollPosition":0}},{"uids":[413],"properties":{"properties":[{"name":"Object type properties","expanded":true,"children":[]},{"name":"Common","expanded":true,"children":[{"name":"Position","expanded":false,"children":[]},{"name":"Size","expanded":false,"children":[]}]},{"name":"Instance variables","expanded":true,"children":[]},{"name":"Behaviors","expanded":true,"children":[{"name":"Solid","expanded":true,"children":[]}]},{"name":"Effects","expanded":true,"children":[]},{"name":"Container","expanded":true,"children":[]},{"name":"Hierarchy","expanded":true,"children":[]},{"name":"Properties","expanded":true,"children":[]}],"scrollPosition":0}},{"uids":[414],"properties":{"properties":[{"name":"Object type properties","expanded":true,"children":[]},{"name":"Common","expanded":true,"children":[{"name":"Position","expanded":false,"children":[]},{"name":"Size","expanded":false,"children":[]}]},{"name":"Instance variables","expanded":true,"children":[]},{"name":"Behaviors","expanded":true,"children":[{"name":"Solid","expanded":true,"children":[]}]},{"name":"Effects","expanded":true,"children":[]},{"name":"Container","expanded":true,"children":[]},{"name":"Hierarchy","expanded":true,"children":[]},{"name":"Properties","expanded":true,"children":[]}],"scrollPosition":0}},{"uids":[418],"properties":{"properties":[{"name":"Object type properties","expanded":true,"children":[]},{"name":"Common","expanded":true,"children":[{"name":"Position","expanded":false,"children":[]},{"name":"Size","expanded":false,"children":[]}]},{"name":"Instance variables","expanded":true,"children":[]},{"name":"Behaviors","expanded":true,"children":[{"name":"Solid","expanded":true,"children":[]}]},{"name":"Effects","expanded":true,"children":[]},{"name":"Container","expanded":true,"children":[]},{"name":"Hierarchy","expanded":true,"children":[]},{"name":"Properties","expanded":true,"children":[]}],"scrollPosition":0}},{"uids":[417],"properties":{"properties":[{"name":"Object type properties","expanded":true,"children":[]},{"name":"Common","expanded":true,"children":[{"name":"Position","expanded":false,"children":[]},{"name":"Size","expanded":false,"children":[]}]},{"name":"Instance variables","expanded":true,"children":[]},{"name":"Behaviors","expanded":true,"children":[{"name":"Solid","expanded":true,"children":[]}]},{"name":"Effects","expanded":true,"children":[]},{"name":"Container","expanded":true,"children":[]},{"name":"Hierarchy","expanded":true,"children":[]},{"name":"Properties","expanded":true,"children":[]}],"scrollPosition":0}},{"uids":[419],"properties":{"properties":[{"name":"Object type properties","expanded":true,"children":[]},{"name":"Common","expanded":true,"children":[{"name":"Position","expanded":false,"children":[]},{"name":"Size","expanded":false,"children":[]}]},{"name":"Instance variables","expanded":true,"children":[]},{"name":"Behaviors","expanded":true,"children":[{"name":"Solid","expanded":true,"children":[]}]},{"name":"Effects","expanded":true,"children":[]},{"name":"Container","expanded":true,"children":[]},{"name":"Properties","expanded":true,"children":[]}],"scrollPosition":0}},{"uids":[420],"properties":{"properties":[{"name":"Object type properties","expanded":true,"children":[]},{"name":"Common","expanded":true,"children":[{"name":"Position","expanded":false,"children":[]},{"name":"Size","expanded":false,"children":[]}]},{"name":"Instance variables","expanded":true,"children":[]},{"name":"Behaviors","expanded":true,"children":[{"name":"Solid","expanded":true,"children":[]}]},{"name":"Effects","expanded":true,"children":[]},{"name":"Container","expanded":true,"children":[]},{"name":"Properties","expanded":true,"children":[]}],"scrollPosition":0}},{"uids":[323],"properties":{"properties":[{"name":"Object type properties","expanded":true,"children":[]},{"name":"Common","expanded":true,"children":[{"name":"Position","expanded":false,"children":[]},{"name":"Size","expanded":false,"children":[]}]},{"name":"Instance variables","expanded":true,"children":[]},{"name":"Behaviors","expanded":true,"children":[{"name":"Solid","expanded":true,"children":[]}]},{"name":"Effects","expanded":true,"children":[]},{"name":"Container","expanded":true,"children":[]},{"name":"Hierarchy","expanded":true,"children":[]},{"name":"Properties","expanded":true,"children":[]}],"scrollPosition":0}},{"uids":[421],"properties":{"properties":[{"name":"Object type properties","expanded":true,"children":[]},{"name":"Common","expanded":true,"children":[{"name":"Position","expanded":false,"children":[]},{"name":"Size","expanded":false,"children":[]}]},{"name":"Instance variables","expanded":true,"children":[]},{"name":"Behaviors","expanded":true,"children":[{"name":"Solid","expanded":true,"children":[]}]},{"name":"Effects","expanded":true,"children":[]},{"name":"Container","expanded":true,"children":[]},{"name":"Hierarchy","expanded":true,"children":[]},{"name":"Properties","expanded":true,"children":[]}],"scrollPosition":0}},{"uids":[425],"properties":{"properties":[{"name":"Object type properties","expanded":true,"children":[]},{"name":"Common","expanded":true,"children":[{"name":"Position","expanded":false,"children":[]},{"name":"Size","expanded":false,"children":[]}]},{"name":"Instance variables","expanded":true,"children":[]},{"name":"Behaviors","expanded":true,"children":[{"name":"Solid","expanded":true,"children":[]}]},{"name":"Effects","expanded":true,"children":[]},{"name":"Container","expanded":true,"children":[]},{"name":"Hierarchy","expanded":true,"children":[]},{"name":"Properties","expanded":true,"children":[]}],"scrollPosition":0}},{"uids":[426],"properties":{"properties":[{"name":"Object type properties","expanded":true,"children":[]},{"name":"Common","expanded":true,"children":[{"name":"Position","expanded":false,"children":[]},{"name":"Size","expanded":false,"children":[]}]},{"name":"Instance variables","expanded":true,"children":[]},{"name":"Behaviors","expanded":true,"children":[{"name":"Solid","expanded":true,"children":[]}]},{"name":"Effects","expanded":true,"children":[]},{"name":"Container","expanded":true,"children":[]},{"name":"Hierarchy","expanded":true,"children":[]},{"name":"Properties","expanded":true,"children":[]}],"scrollPosition":0}},{"uids":[427],"properties":{"properties":[{"name":"Object type properties","expanded":true,"children":[]},{"name":"Common","expanded":true,"children":[{"name":"Position","expanded":false,"children":[]},{"name":"Size","expanded":false,"children":[]}]},{"name":"Instance variables","expanded":true,"children":[]},{"name":"Behaviors","expanded":true,"children":[{"name":"Solid","expanded":true,"children":[]}]},{"name":"Effects","expanded":true,"children":[]},{"name":"Container","expanded":true,"children":[]},{"name":"Hierarchy","expanded":true,"children":[]},{"name":"Properties","expanded":true,"children":[]}],"scrollPosition":0}},{"uids":[70],"properties":{"properties":[{"name":"Object type properties","expanded":true,"children":[]},{"name":"Common","expanded":true,"children":[{"name":"Position","expanded":false,"children":[]},{"name":"Size","expanded":false,"children":[]}]},{"name":"Instance variables","expanded":true,"children":[]},{"name":"Behaviors","expanded":true,"children":[{"name":"Solid","expanded":true,"children":[]}]},{"name":"Effects","expanded":true,"children":[]},{"name":"Container","expanded":true,"children":[]},{"name":"Hierarchy","expanded":true,"children":[]},{"name":"Properties","expanded":true,"children":[]}],"scrollPosition":0}},{"uids":[259],"properties":{"properties":[{"name":"Object type properties","expanded":true,"children":[]},{"name":"Common","expanded":true,"children":[{"name":"Position","expanded":false,"children":[]},{"name":"Size","expanded":false,"children":[]}]},{"name":"Instance variables","expanded":true,"children":[]},{"name":"Behaviors","expanded":true,"children":[{"name":"Solid","expanded":true,"children":[]}]},{"name":"Effects","expanded":true,"children":[]},{"name":"Container","expanded":true,"children":[]},{"name":"Properties","expanded":true,"children":[]}],"scrollPosition":0}},{"uids":[257],"properties":{"properties":[{"name":"Object type properties","expanded":true,"children":[]},{"name":"Common","expanded":true,"children":[{"name":"Position","expanded":false,"children":[]},{"name":"Size","expanded":false,"children":[]}]},{"name":"Instance variables","expanded":true,"children":[]},{"name":"Behaviors","expanded":true,"children":[{"name":"Solid","expanded":true,"children":[]}]},{"name":"Effects","expanded":true,"children":[]},{"name":"Container","expanded":true,"children":[]},{"name":"Properties","expanded":true,"children":[]}],"scrollPosition":0}},{"uids":[430],"properties":{"properties":[{"name":"Object type properties","expanded":true,"children":[]},{"name":"Common","expanded":true,"children":[{"name":"Position","expanded":false,"children":[]},{"name":"Size","expanded":false,"children":[]}]},{"name":"Instance variables","expanded":true,"children":[]},{"name":"Behaviors","expanded":true,"children":[{"name":"Solid","expanded":true,"children":[]}]},{"name":"Effects","expanded":true,"children":[]},{"name":"Container","expanded":true,"children":[]},{"name":"Hierarchy","expanded":true,"children":[]},{"name":"Properties","expanded":true,"children":[]}],"scrollPosition":0}},{"uids":[74],"properties":{"properties":[{"name":"Object type properties","expanded":true,"children":[]},{"name":"Common","expanded":true,"children":[{"name":"Position","expanded":false,"children":[]},{"name":"Size","expanded":false,"children":[]}]},{"name":"Instance variables","expanded":true,"children":[{"name":"Inherited from 'fEnemies'","expanded":true,"children":[]}]},{"name":"Behaviors","expanded":true,"children":[{"name":"Tween [fEnemies]","expanded":true,"children":[]}]},{"name":"Effects","expanded":true,"children":[]},{"name":"Container","expanded":true,"children":[]},{"name":"Hierarchy","expanded":true,"children":[]},{"name":"Properties","expanded":true,"children":[]}],"scrollPosition":0}},{"uids":[317],"properties":{"properties":[{"name":"Object type properties","expanded":true,"children":[]},{"name":"Common","expanded":true,"children":[{"name":"Position","expanded":false,"children":[]},{"name":"Size","expanded":false,"children":[]}]},{"name":"Instance variables","expanded":true,"children":[{"name":"Inherited from 'fEnemies'","expanded":true,"children":[]}]},{"name":"Behaviors","expanded":true,"children":[{"name":"Tween [fEnemies]","expanded":true,"children":[]}]},{"name":"Effects","expanded":true,"children":[]},{"name":"Container","expanded":true,"children":[]},{"name":"Hierarchy","expanded":true,"children":[]},{"name":"Properties","expanded":true,"children":[]}],"scrollPosition":0}},{"uids":[428],"properties":{"properties":[{"name":"Object type properties","expanded":true,"children":[]},{"name":"Common","expanded":true,"children":[{"name":"Position","expanded":false,"children":[]},{"name":"Size","expanded":false,"children":[]}]},{"name":"Instance variables","expanded":true,"children":[]},{"name":"Behaviors","expanded":true,"children":[{"name":"Solid","expanded":true,"children":[]}]},{"name":"Effects","expanded":true,"children":[]},{"name":"Container","expanded":true,"children":[]},{"name":"Hierarchy","expanded":true,"children":[]},{"name":"Properties","expanded":true,"children":[]}],"scrollPosition":0}},{"uids":[431],"properties":{"properties":[{"name":"Object type properties","expanded":true,"children":[]},{"name":"Common","expanded":true,"children":[{"name":"Position","expanded":false,"children":[]},{"name":"Size","expanded":false,"children":[]}]},{"name":"Instance variables","expanded":true,"children":[{"name":"Inherited from 'fEnemies'","expanded":true,"children":[]}]},{"name":"Behaviors","expanded":true,"children":[{"name":"Tween [fEnemies]","expanded":true,"children":[]}]},{"name":"Effects","expanded":true,"children":[]},{"name":"Container","expanded":true,"children":[]},{"name":"Hierarchy","expanded":true,"children":[]},{"name":"Properties","expanded":true,"children":[]}],"scrollPosition":0}},{"uids":[423],"properties":{"properties":[{"name":"Object type properties","expanded":true,"children":[]},{"name":"Common","expanded":true,"children":[{"name":"Position","expanded":false,"children":[]},{"name":"Size","expanded":false,"children":[]}]},{"name":"Instance variables","expanded":true,"children":[]},{"name":"Behaviors","expanded":true,"children":[{"name":"Solid","expanded":true,"children":[]}]},{"name":"Effects","expanded":true,"children":[]},{"name":"Container","expanded":true,"children":[]},{"name":"Hierarchy","expanded":true,"children":[]},{"name":"Properties","expanded":true,"children":[]}],"scrollPosition":0}},{"uids":[424],"properties":{"properties":[{"name":"Object type properties","expanded":true,"children":[]},{"name":"Common","expanded":true,"children":[{"name":"Position","expanded":false,"children":[]},{"name":"Size","expanded":false,"children":[]}]},{"name":"Instance variables","expanded":true,"children":[]},{"name":"Behaviors","expanded":true,"children":[{"name":"Solid","expanded":true,"children":[]}]},{"name":"Effects","expanded":true,"children":[]},{"name":"Container","expanded":true,"children":[]},{"name":"Hierarchy","expanded":true,"children":[]},{"name":"Properties","expanded":true,"children":[]}],"scrollPosition":0}},{"uids":[320],"properties":{"properties":[{"name":"Object type properties","expanded":true,"children":[]},{"name":"Common","expanded":true,"children":[{"name":"Position","expanded":false,"children":[]},{"name":"Size","expanded":false,"children":[]}]},{"name":"Instance variables","expanded":true,"children":[{"name":"Inherited from 'fEnemies'","expanded":true,"children":[]}]},{"name":"Behaviors","expanded":true,"children":[{"name":"Tween [fEnemies]","expanded":true,"children":[]}]},{"name":"Effects","expanded":true,"children":[]},{"name":"Container","expanded":true,"children":[]},{"name":"Hierarchy","expanded":true,"children":[]},{"name":"Properties","expanded":true,"children":[]}],"scrollPosition":0}},{"uids":[422],"properties":{"properties":[{"name":"Object type properties","expanded":true,"children":[]},{"name":"Common","expanded":true,"children":[{"name":"Position","expanded":false,"children":[]},{"name":"Size","expanded":false,"children":[]}]},{"name":"Instance variables","expanded":true,"children":[]},{"name":"Behaviors","expanded":true,"children":[{"name":"Solid","expanded":true,"children":[]}]},{"name":"Effects","expanded":true,"children":[]},{"name":"Container","expanded":true,"children":[]},{"name":"Hierarchy","expanded":true,"children":[]},{"name":"Properties","expanded":true,"children":[]}],"scrollPosition":0}},{"uids":[77],"properties":{"properties":[{"name":"Object type properties","expanded":true,"children":[]},{"name":"Common","expanded":true,"children":[{"name":"Position","expanded":false,"children":[]},{"name":"Size","expanded":false,"children":[]}]},{"name":"Instance variables","expanded":true,"children":[{"name":"Inherited from 'fEnemies'","expanded":true,"children":[]}]},{"name":"Behaviors","expanded":true,"children":[{"name":"Tween [fEnemies]","expanded":true,"children":[]}]},{"name":"Effects","expanded":true,"children":[]},{"name":"Container","expanded":true,"children":[]},{"name":"Hierarchy","expanded":true,"children":[]},{"name":"Properties","expanded":true,"children":[]}],"scrollPosition":0}},{"uids":[241],"properties":{"properties":[{"name":"Object type properties","expanded":true,"children":[]},{"name":"Common","expanded":true,"children":[{"name":"Position","expanded":false,"children":[]},{"name":"Size","expanded":false,"children":[]}]},{"name":"Instance variables","expanded":true,"children":[]},{"name":"Behaviors","expanded":true,"children":[]},{"name":"Effects","expanded":true,"children":[]},{"name":"Container","expanded":true,"children":[]},{"name":"Properties","expanded":true,"children":[]}],"scrollPosition":0}},{"uids":[264],"properties":{"properties":[{"name":"Object type properties","expanded":true,"children":[]},{"name":"Common","expanded":true,"children":[{"name":"Position","expanded":false,"children":[]},{"name":"Size","expanded":false,"children":[]}]},{"name":"Instance variables","expanded":true,"children":[]},{"name":"Behaviors","expanded":true,"children":[]},{"name":"Effects","expanded":true,"children":[]},{"name":"Container","expanded":true,"children":[]},{"name":"Properties","expanded":true,"children":[]}],"scrollPosition":0}},{"uids":[264],"properties":{"properties":[{"name":"Object type properties","expanded":true,"children":[]},{"name":"Common","expanded":true,"children":[{"name":"Position","expanded":false,"children":[]},{"name":"Size","expanded":false,"children":[]}]},{"name":"Instance variables","expanded":true,"children":[]},{"name":"Behaviors","expanded":true,"children":[]},{"name":"Effects","expanded":true,"children":[]},{"name":"Container","expanded":true,"children":[]},{"name":"Properties","expanded":true,"children":[]}],"scrollPosition":0}},{"uids":[262],"properties":{"properties":[{"name":"Object type properties","expanded":true,"children":[]},{"name":"Common","expanded":true,"children":[{"name":"Position","expanded":false,"children":[]},{"name":"Size","expanded":false,"children":[]}]},{"name":"Instance variables","expanded":true,"children":[]},{"name":"Behaviors","expanded":true,"children":[]},{"name":"Effects","expanded":true,"children":[]},{"name":"Container","expanded":true,"children":[]},{"name":"Properties","expanded":true,"children":[]},{"name":"Image transform","expanded":true,"children":[]}],"scrollPosition":0}},{"uids":[263],"properties":{"properties":[{"name":"Object type properties","expanded":true,"children":[]},{"name":"Common","expanded":true,"children":[{"name":"Position","expanded":false,"children":[]},{"name":"Size","expanded":false,"children":[]}]},{"name":"Instance variables","expanded":true,"children":[]},{"name":"Behaviors","expanded":true,"children":[{"name":"Pin","expanded":true,"children":[]}]},{"name":"Effects","expanded":true,"children":[]},{"name":"Container","expanded":true,"children":[]},{"name":"Properties","expanded":true,"children":[]}],"scrollPosition":3}},{"uids":[268],"properties":{"properties":[{"name":"Object type properties","expanded":true,"children":[]},{"name":"Common","expanded":true,"children":[{"name":"Position","expanded":false,"children":[]},{"name":"Size","expanded":false,"children":[]}]},{"name":"Instance variables","expanded":true,"children":[]},{"name":"Behaviors","expanded":true,"children":[{"name":"Custom","expanded":true,"children":[]},{"name":"LineOfSight","expanded":true,"children":[]},{"name":"Tween","expanded":true,"children":[]}]},{"name":"Effects","expanded":true,"children":[]},{"name":"Container","expanded":true,"children":[]},{"name":"Properties","expanded":true,"children":[]}],"scrollPosition":0}},{"uids":[274],"properties":{"properties":[{"name":"Object type properties","expanded":true,"children":[]},{"name":"Common","expanded":true,"children":[{"name":"Position","expanded":false,"children":[]},{"name":"Size","expanded":false,"children":[]}]},{"name":"Instance variables","expanded":true,"children":[]},{"name":"Behaviors","expanded":true,"children":[{"name":"Pin","expanded":true,"children":[]}]},{"name":"Effects","expanded":true,"children":[]},{"name":"Container","expanded":true,"children":[]},{"name":"Properties","expanded":true,"children":[]},{"name":"Initial particle properties","expanded":true,"children":[]},{"name":"Particle lifetime properties","expanded":true,"children":[]}],"scrollPosition":0}},{"uids":[272],"properties":{"properties":[{"name":"Object type properties","expanded":true,"children":[]},{"name":"Common","expanded":true,"children":[{"name":"Position","expanded":false,"children":[]},{"name":"Size","expanded":false,"children":[]}]},{"name":"Instance variables","expanded":true,"children":[]},{"name":"Behaviors","expanded":true,"children":[]},{"name":"Effects","expanded":true,"children":[]},{"name":"Container","expanded":true,"children":[]},{"name":"Properties","expanded":true,"children":[]}],"scrollPosition":0}},{"uids":[415],"properties":{"properties":[{"name":"Object type properties","expanded":true,"children":[]},{"name":"Common","expanded":true,"children":[{"name":"Position","expanded":false,"children":[]},{"name":"Size","expanded":false,"children":[]}]},{"name":"Instance variables","expanded":true,"children":[]},{"name":"Behaviors","expanded":true,"children":[]},{"name":"Effects","expanded":true,"children":[]},{"name":"Container","expanded":true,"children":[]},{"name":"Properties","expanded":true,"children":[]}],"scrollPosition":0}},{"uids":[416],"properties":{"properties":[{"name":"Object type properties","expanded":true,"children":[]},{"name":"Common","expanded":true,"children":[{"name":"Position","expanded":false,"children":[]},{"name":"Size","expanded":false,"children":[]}]},{"name":"Instance variables","expanded":true,"children":[]},{"name":"Behaviors","expanded":true,"children":[]},{"name":"Effects","expanded":true,"children":[]},{"name":"Container","expanded":true,"children":[]},{"name":"Properties","expanded":true,"children":[]}],"scrollPosition":0}},{"uids":[270],"properties":{"properties":[{"name":"Object type properties","expanded":true,"children":[]},{"name":"Common","expanded":true,"children":[{"name":"Position","expanded":false,"children":[]},{"name":"Size","expanded":false,"children":[]}]},{"name":"Instance variables","expanded":true,"children":[]},{"name":"Behaviors","expanded":true,"children":[{"name":"Solid","expanded":true,"children":[]}]},{"name":"Effects","expanded":true,"children":[]},{"name":"Container","expanded":true,"children":[]},{"name":"Hierarchy","expanded":true,"children":[]},{"name":"Properties","expanded":true,"children":[]}],"scrollPosition":0}},{"uids":[270],"properties":{"properties":[{"name":"Object type properties","expanded":true,"children":[]},{"name":"Common","expanded":true,"children":[{"name":"Position","expanded":false,"children":[]},{"name":"Size","expanded":false,"children":[]}]},{"name":"Instance variables","expanded":true,"children":[]},{"name":"Behaviors","expanded":true,"children":[{"name":"Solid","expanded":true,"children":[]}]},{"name":"Effects","expanded":true,"children":[]},{"name":"Container","expanded":true,"children":[]},{"name":"Hierarchy","expanded":true,"children":[]},{"name":"Properties","expanded":true,"children":[]}],"scrollPosition":0}},{"uids":[255],"properties":{"properties":[{"name":"Object type properties","expanded":true,"children":[]},{"name":"Common","expanded":true,"children":[{"name":"Position","expanded":false,"children":[]},{"name":"Size","expanded":false,"children":[]}]},{"name":"Instance variables","expanded":true,"children":[]},{"name":"Behaviors","expanded":true,"children":[{"name":"Solid","expanded":true,"children":[]}]},{"name":"Effects","expanded":true,"children":[]},{"name":"Container","expanded":true,"children":[]},{"name":"Properties","expanded":true,"children":[]}],"scrollPosition":0}},{"uids":[255],"properties":{"properties":[{"name":"Object type properties","expanded":true,"children":[]},{"name":"Common","expanded":true,"children":[{"name":"Position","expanded":false,"children":[]},{"name":"Size","expanded":false,"children":[]}]},{"name":"Instance variables","expanded":true,"children":[]},{"name":"Behaviors","expanded":true,"children":[{"name":"Solid","expanded":true,"children":[]}]},{"name":"Effects","expanded":true,"children":[]},{"name":"Container","expanded":true,"children":[]},{"name":"Properties","expanded":true,"children":[]}],"scrollPosition":0}},{"uids":[80],"properties":{"properties":[{"name":"Object type properties","expanded":true,"children":[]},{"name":"Common","expanded":true,"children":[{"name":"Position","expanded":false,"children":[]},{"name":"Size","expanded":false,"children":[]}]},{"name":"Instance variables","expanded":true,"children":[]},{"name":"Behaviors","expanded":true,"children":[{"name":"Solid","expanded":true,"children":[]}]},{"name":"Effects","expanded":true,"children":[]},{"name":"Container","expanded":true,"children":[]},{"name":"Hierarchy","expanded":true,"children":[]},{"name":"Properties","expanded":true,"children":[]}],"scrollPosition":0}},{"uids":[73],"properties":{"properties":[{"name":"Object type properties","expanded":true,"children":[]},{"name":"Common","expanded":true,"children":[{"name":"Position","expanded":false,"children":[]},{"name":"Size","expanded":false,"children":[]}]},{"name":"Instance variables","expanded":true,"children":[]},{"name":"Behaviors","expanded":true,"children":[{"name":"Solid","expanded":true,"children":[]}]},{"name":"Effects","expanded":true,"children":[]},{"name":"Container","expanded":true,"children":[]},{"name":"Hierarchy","expanded":true,"children":[]},{"name":"Properties","expanded":true,"children":[]}],"scrollPosition":0}},{"uids":[76],"properties":{"properties":[{"name":"Object type properties","expanded":true,"children":[]},{"name":"Common","expanded":true,"children":[{"name":"Position","expanded":false,"children":[]},{"name":"Size","expanded":false,"children":[]}]},{"name":"Instance variables","expanded":true,"children":[]},{"name":"Behaviors","expanded":true,"children":[{"name":"Solid","expanded":true,"children":[]}]},{"name":"Effects","expanded":true,"children":[]},{"name":"Container","expanded":true,"children":[]},{"name":"Hierarchy","expanded":true,"children":[]},{"name":"Properties","expanded":true,"children":[]}],"scrollPosition":0}},{"uids":[15],"properties":{"properties":[{"name":"Object type properties","expanded":true,"children":[]},{"name":"Common","expanded":true,"children":[{"name":"Position","expanded":false,"children":[]},{"name":"Size","expanded":false,"children":[]}]},{"name":"Instance variables","expanded":true,"children":[]},{"name":"Behaviors","expanded":true,"children":[{"name":"Solid","expanded":true,"children":[]}]},{"name":"Effects","expanded":true,"children":[]},{"name":"Container","expanded":true,"children":[]},{"name":"Hierarchy","expanded":true,"children":[]},{"name":"Properties","expanded":true,"children":[]}],"scrollPosition":0}},{"uids":[74],"properties":{"properties":[{"name":"Object type properties","expanded":true,"children":[]},{"name":"Common","expanded":true,"children":[{"name":"Position","expanded":false,"children":[]},{"name":"Size","expanded":false,"children":[]}]},{"name":"Instance variables","expanded":true,"children":[{"name":"Inherited from 'fEnemies'","expanded":true,"children":[]}]},{"name":"Behaviors","expanded":true,"children":[{"name":"Tween [fEnemies]","expanded":true,"children":[]}]},{"name":"Effects","expanded":true,"children":[]},{"name":"Container","expanded":true,"children":[]},{"name":"Hierarchy","expanded":true,"children":[]},{"name":"Properties","expanded":true,"children":[]}],"scrollPosition":0}},{"uids":[242],"properties":{"properties":[{"name":"Object type properties","expanded":true,"children":[]},{"name":"Common","expanded":true,"children":[{"name":"Position","expanded":false,"children":[]},{"name":"Size","expanded":false,"children":[]}]},{"name":"Instance variables","expanded":true,"children":[]},{"name":"Behaviors","expanded":true,"children":[]},{"name":"Effects","expanded":true,"children":[]},{"name":"Container","expanded":true,"children":[]},{"name":"Properties","expanded":true,"children":[]},{"name":"Image transform","expanded":true,"children":[]}],"scrollPosition":0}},{"uids":[411],"properties":{"properties":[{"name":"Object type properties","expanded":true,"children":[]},{"name":"Common","expanded":true,"children":[{"name":"Position","expanded":false,"children":[]},{"name":"Size","expanded":false,"children":[]}]},{"name":"Instance variables","expanded":true,"children":[]},{"name":"Behaviors","expanded":true,"children":[{"name":"Solid","expanded":true,"children":[]}]},{"name":"Effects","expanded":true,"children":[]},{"name":"Container","expanded":true,"children":[]},{"name":"Hierarchy","expanded":true,"children":[]},{"name":"Properties","expanded":true,"children":[]}],"scrollPosition":0}},{"uids":[260,314,325],"properties":{"properties":[{"name":"Object type properties","expanded":true,"children":[]},{"name":"Common","expanded":true,"children":[{"name":"Position","expanded":false,"children":[]},{"name":"Size","expanded":false,"children":[]}]},{"name":"Instance variables","expanded":true,"children":[]},{"name":"Behaviors","expanded":true,"children":[{"name":"Solid","expanded":true,"children":[]}]},{"name":"Effects","expanded":true,"children":[]},{"name":"Container","expanded":true,"children":[]},{"name":"Properties","expanded":true,"children":[]}],"scrollPosition":0}},{"uids":[326,327,328],"properties":{"properties":[{"name":"Object type properties","expanded":true,"children":[]},{"name":"Common","expanded":true,"children":[{"name":"Position","expanded":false,"children":[]},{"name":"Size","expanded":false,"children":[]}]},{"name":"Instance variables","expanded":true,"children":[]},{"name":"Behaviors","expanded":true,"children":[{"name":"Solid","expanded":true,"children":[]}]},{"name":"Effects","expanded":true,"children":[]},{"name":"Container","expanded":true,"children":[]},{"name":"Properties","expanded":true,"children":[]}],"scrollPosition":0}},{"uids":[259,261],"properties":{"properties":[{"name":"Object type properties","expanded":true,"children":[]},{"name":"Common","expanded":true,"children":[{"name":"Position","expanded":false,"children":[]},{"name":"Size","expanded":false,"children":[]}]},{"name":"Instance variables","expanded":true,"children":[{"name":"Inherited from 'fEnemies'","expanded":true,"children":[]}]},{"name":"Behaviors","expanded":true,"children":[{"name":"Tween [fEnemies]","expanded":true,"children":[]}]},{"name":"Effects","expanded":true,"children":[]},{"name":"Container","expanded":true,"children":[]},{"name":"Hierarchy","expanded":true,"children":[]},{"name":"Properties","expanded":true,"children":[]}],"scrollPosition":0}},{"uids":[254,255,310],"properties":{"properties":[{"name":"Object type properties","expanded":true,"children":[]},{"name":"Common","expanded":true,"children":[{"name":"Position","expanded":false,"children":[]},{"name":"Size","expanded":false,"children":[]}]},{"name":"Instance variables","expanded":true,"children":[]},{"name":"Behaviors","expanded":true,"children":[{"name":"Solid","expanded":true,"children":[]}]},{"name":"Effects","expanded":true,"children":[]},{"name":"Container","expanded":true,"children":[]},{"name":"Properties","expanded":true,"children":[]}],"scrollPosition":0}},{"uids":[254,255,311],"properties":{"properties":[{"name":"Object type properties","expanded":true,"children":[]},{"name":"Common","expanded":true,"children":[{"name":"Position","expanded":false,"children":[]},{"name":"Size","expanded":false,"children":[]}]},{"name":"Instance variables","expanded":true,"children":[]},{"name":"Behaviors","expanded":true,"children":[{"name":"Solid","expanded":true,"children":[]}]},{"name":"Effects","expanded":true,"children":[]},{"name":"Container","expanded":true,"children":[]},{"name":"Properties","expanded":true,"children":[]}],"scrollPosition":0}},{"uids":[254,310,311],"properties":{"properties":[{"name":"Object type properties","expanded":true,"children":[]},{"name":"Common","expanded":true,"children":[{"name":"Position","expanded":false,"children":[]},{"name":"Size","expanded":false,"children":[]}]},{"name":"Instance variables","expanded":true,"children":[]},{"name":"Behaviors","expanded":true,"children":[{"name":"Solid","expanded":true,"children":[]}]},{"name":"Effects","expanded":true,"children":[]},{"name":"Container","expanded":true,"children":[]},{"name":"Properties","expanded":true,"children":[]}],"scrollPosition":0}},{"uids":[241,264,265],"properties":{"properties":[{"name":"Family properties","expanded":true,"children":[]},{"name":"Common","expanded":true,"children":[{"name":"Position","expanded":false,"children":[]},{"name":"Size","expanded":false,"children":[]}]},{"name":"Family instance variables","expanded":true,"children":[]},{"name":"Family behaviors","expanded":true,"children":[]},{"name":"Family effects","expanded":true,"children":[]},{"name":"Properties","expanded":true,"children":[]}],"scrollPosition":0}},{"uids":[312,313,315],"properties":{"properties":[{"name":"Object type properties","expanded":true,"children":[]},{"name":"Common","expanded":true,"children":[{"name":"Position","expanded":false,"children":[]},{"name":"Size","expanded":false,"children":[]}]},{"name":"Instance variables","expanded":true,"children":[{"name":"Inherited from 'fEnemies'","expanded":true,"children":[]}]},{"name":"Behaviors","expanded":true,"children":[{"name":"Tween [fEnemies]","expanded":true,"children":[]}]},{"name":"Effects","expanded":true,"children":[]},{"name":"Container","expanded":true,"children":[]},{"name":"Hierarchy","expanded":true,"children":[]},{"name":"Properties","expanded":true,"children":[]}],"scrollPosition":0}},{"uids":[78],"properties":{"properties":[{"name":"Object type properties","expanded":true,"children":[]},{"name":"Common","expanded":true,"children":[{"name":"Position","expanded":false,"children":[]},{"name":"Size","expanded":false,"children":[]}]},{"name":"Instance variables","expanded":true,"children":[]},{"name":"Behaviors","expanded":true,"children":[]},{"name":"Effects","expanded":true,"children":[]},{"name":"Container","expanded":true,"children":[]},{"name":"Properties","expanded":true,"children":[]}],"scrollPosition":0}},{"uids":[86],"properties":{"properties":[{"name":"Object type properties","expanded":true,"children":[]},{"name":"Common","expanded":true,"children":[{"name":"Position","expanded":false,"children":[]},{"name":"Size","expanded":false,"children":[]}]},{"name":"Instance variables","expanded":true,"children":[]},{"name":"Behaviors","expanded":true,"children":[]},{"name":"Effects","expanded":true,"children":[]},{"name":"Container","expanded":true,"children":[]},{"name":"Properties","expanded":true,"children":[]}],"scrollPosition":0}},{"uids":[271],"properties":{"properties":[{"name":"Object type properties","expanded":true,"children":[]},{"name":"Common","expanded":true,"children":[{"name":"Position","expanded":false,"children":[]},{"name":"Size","expanded":false,"children":[]}]},{"name":"Instance variables","expanded":true,"children":[]},{"name":"Behaviors","expanded":true,"children":[{"name":"Tween","expanded":true,"children":[]}]},{"name":"Effects","expanded":true,"children":[]},{"name":"Container","expanded":true,"children":[]},{"name":"Properties","expanded":true,"children":[]}],"scrollPosition":0}},{"uids":[318],"properties":{"properties":[{"name":"Object type properties","expanded":true,"children":[]},{"name":"Common","expanded":true,"children":[{"name":"Position","expanded":false,"children":[]},{"name":"Size","expanded":false,"children":[]}]},{"name":"Instance variables","expanded":true,"children":[{"name":"Inherited from 'fEnemies'","expanded":true,"children":[]}]},{"name":"Behaviors","expanded":true,"children":[{"name":"Tween [fEnemies]","expanded":true,"children":[]},{"name":"Sine [fEnemies]","expanded":true,"children":[]}]},{"name":"Effects","expanded":true,"children":[]},{"name":"Container","expanded":true,"children":[]},{"name":"Hierarchy","expanded":true,"children":[]},{"name":"Properties","expanded":true,"children":[]}],"scrollPosition":0}},{"uids":[74,77,243,249,316,317,318,320,431],"properties":{"properties":[{"name":"Object type properties","expanded":true,"children":[]},{"name":"Common","expanded":true,"children":[{"name":"Position","expanded":false,"children":[]},{"name":"Size","expanded":false,"children":[]}]},{"name":"Instance variables","expanded":true,"children":[{"name":"Inherited from 'fEnemies'","expanded":true,"children":[]}]},{"name":"Behaviors","expanded":true,"children":[{"name":"Tween [fEnemies]","expanded":true,"children":[]},{"name":"Sine [fEnemies]","expanded":true,"children":[]}]},{"name":"Effects","expanded":true,"children":[]},{"name":"Container","expanded":true,"children":[]},{"name":"Hierarchy","expanded":true,"children":[]},{"name":"Properties","expanded":true,"children":[]}],"scrollPosition":0}},{"uids":[326],"properties":{"properties":[{"name":"Object type properties","expanded":true,"children":[]},{"name":"Common","expanded":true,"children":[{"name":"Position","expanded":false,"children":[]},{"name":"Size","expanded":false,"children":[]}]},{"name":"Instance variables","expanded":true,"children":[]},{"name":"Behaviors","expanded":true,"children":[{"name":"Solid","expanded":true,"children":[]}]},{"name":"Effects","expanded":true,"children":[]},{"name":"Container","expanded":true,"children":[]},{"name":"Hierarchy","expanded":true,"children":[]},{"name":"Properties","expanded":true,"children":[]}],"scrollPosition":0}},{"uids":[326],"properties":{"properties":[{"name":"Object type properties","expanded":true,"children":[]},{"name":"Common","expanded":true,"children":[{"name":"Position","expanded":false,"children":[]},{"name":"Size","expanded":false,"children":[]}]},{"name":"Instance variables","expanded":true,"children":[]},{"name":"Behaviors","expanded":true,"children":[{"name":"Solid","expanded":true,"children":[]}]},{"name":"Effects","expanded":true,"children":[]},{"name":"Container","expanded":true,"children":[]},{"name":"Hierarchy","expanded":true,"children":[]},{"name":"Properties","expanded":true,"children":[]}],"scrollPosition":0}},{"uids":[275],"properties":{"properties":[{"name":"Object type properties","expanded":true,"children":[]},{"name":"Common","expanded":true,"children":[{"name":"Position","expanded":false,"children":[]},{"name":"Size","expanded":false,"children":[]}]},{"name":"Instance variables","expanded":true,"children":[]},{"name":"Behaviors","expanded":true,"children":[{"name":"Solid","expanded":true,"children":[]}]},{"name":"Effects","expanded":true,"children":[]},{"name":"Container","expanded":true,"children":[]},{"name":"Hierarchy","expanded":true,"children":[]},{"name":"Properties","expanded":true,"children":[]}],"scrollPosition":0}},{"uids":[275],"properties":{"properties":[{"name":"Object type properties","expanded":true,"children":[]},{"name":"Common","expanded":true,"children":[{"name":"Position","expanded":false,"children":[]},{"name":"Size","expanded":false,"children":[]}]},{"name":"Instance variables","expanded":true,"children":[]},{"name":"Behaviors","expanded":true,"children":[{"name":"Solid","expanded":true,"children":[]}]},{"name":"Effects","expanded":true,"children":[]},{"name":"Container","expanded":true,"children":[]},{"name":"Hierarchy","expanded":true,"children":[]},{"name":"Properties","expanded":true,"children":[]}],"scrollPosition":0}},{"uids":[314],"properties":{"properties":[{"name":"Object type properties","expanded":true,"children":[]},{"name":"Common","expanded":true,"children":[{"name":"Position","expanded":false,"children":[]},{"name":"Size","expanded":false,"children":[]}]},{"name":"Instance variables","expanded":true,"children":[]},{"name":"Behaviors","expanded":true,"children":[{"name":"Solid","expanded":true,"children":[]}]},{"name":"Effects","expanded":true,"children":[]},{"name":"Container","expanded":true,"children":[]},{"name":"Hierarchy","expanded":true,"children":[]},{"name":"Properties","expanded":true,"children":[]}],"scrollPosition":0}},{"uids":[314],"properties":{"properties":[{"name":"Object type properties","expanded":true,"children":[]},{"name":"Common","expanded":true,"children":[{"name":"Position","expanded":false,"children":[]},{"name":"Size","expanded":false,"children":[]}]},{"name":"Instance variables","expanded":true,"children":[]},{"name":"Behaviors","expanded":true,"children":[{"name":"Solid","expanded":true,"children":[]}]},{"name":"Effects","expanded":true,"children":[]},{"name":"Container","expanded":true,"children":[]},{"name":"Hierarchy","expanded":true,"children":[]},{"name":"Properties","expanded":true,"children":[]}],"scrollPosition":0}},{"uids":[254],"properties":{"properties":[{"name":"Object type properties","expanded":true,"children":[]},{"name":"Common","expanded":true,"children":[{"name":"Position","expanded":false,"children":[]},{"name":"Size","expanded":false,"children":[]}]},{"name":"Instance variables","expanded":true,"children":[]},{"name":"Behaviors","expanded":true,"children":[{"name":"Solid","expanded":true,"children":[]}]},{"name":"Effects","expanded":true,"children":[]},{"name":"Container","expanded":true,"children":[]},{"name":"Properties","expanded":true,"children":[]}],"scrollPosition":0}}]}